folderfolder/__init__.py
folderfolder/folderclass.py
folderfolder-0.0.2.dist-info/LICENSE
folderfolder-0.0.2.dist-info/METADATA
folderfolder-0.0.2.dist-info/WHEEL
folderfolder-0.0.2.dist-info/top_level.txt
folderfolder-0.0.2.dist-info/RECORD
