Metadata-Version: 2.1
Name: folderfolder
Version: 0.0.2
Summary: A package for manipulating large folder structures
Home-page: https://github.com/asras/folderfolder
Author: Asbjorn Rasmussen
Author-email: asras28@gmail.com
License: UNKNOWN
Platform: UNKNOWN
Classifier: Programming Language :: Python :: 3
Classifier: License :: OSI Approved :: MIT License
Classifier: Operating System :: OS Independent
Requires-Python: >=3.5
